biosound/__about__.py
biosound/__init__.py
biosound/annotation.py
biosound/annotation_file.py
biosound/annotator.py
biosound/audio_file.py
biosound/constants.py
biosound/dataset_file.py
biosound/feature_extractor.py
biosound/feature_file.py
biosound/features.py
biosound/params.py
biosound/paths.py
biosound/segmenter.py
biosound/segments.py
biosound/sequence.py
biosound/sound.py
biosound/spectrogram.py
biosound/spectrogram_file.py
biosound/spectrogram_maker.py
biosound/spectrogram_parameters.py
biosound/unit.py
biosound/_spectrogram/__init__.py
biosound/_spectrogram/data_type.py
biosound/_vendor/__init__.py
biosound/_vendor/evfuncs.py
biosound/examples/BM003.wav
biosound/examples/BM003.wav.description.txt
biosound/examples/WhiLbl0010.description.txt
biosound/examples/WhiLbl0010_110411-DC-01.wav
biosound/examples/__init__.py
biosound/examples/_examples.py
biosound/examples/bells.wav
biosound/examples/bfsongrepo.description.txt
biosound/examples/bl26lb16.wav
biosound/examples/bl26lb16.wav.description.txt
biosound/examples/deermouse-go.wav
biosound/examples/deermouse-go.wav.description.txt
biosound/examples/example-metadata.json
biosound/examples/example_data.py
biosound/examples/flashcam.wav
biosound/examples/fruitfly-song-multichannel.wav
biosound/examples/fruitfly-song-multichannel.wav.description.txt
biosound/examples/samba.wav
biosound/examples/simple.wav
biosound/examples/twopup.description.txt
biosound/examples/zblib.description.txt
biosound/examples/zebra-finch-SAP.description.txt
biosound/feature/__init__.py
biosound/feature/_sat.py
biosound/feature/_biosound/__init__.py
biosound/feature/_biosound/constants.py
biosound/feature/_biosound/detect_peaks.py
biosound/feature/_biosound/features.py
biosound/feature/_biosound/fundamental.py
biosound/feature/_biosound/signal.py
biosound/feature/_biosound/sound.py
biosound/metrics/__init__.py
biosound/metrics/segmentation/__init__.py
biosound/metrics/segmentation/ir.py
biosound/plot/__init__.py
biosound/plot/annot.py
biosound-0.10.0.post1.dist-info/LICENSE
biosound-0.10.0.post1.dist-info/WHEEL
biosound-0.10.0.post1.dist-info/METADATA
biosound-0.10.0.post1.dist-info/RECORD
