Metadata-Version: 2.1
Name: biosound
Version: 0.10.0.post1
Summary: A core package for acoustic communication research in Python
Author-email: David Nicholson <nickledave@users.noreply.github.com>
Requires-Python: >=3.10
Classifier: License :: OSI Approved :: BSD License
Classifier: Development Status :: 5 - Production/Stable
Classifier: Programming Language :: Python
Classifier: Programming Language :: Python :: 3
Classifier: Programming Language :: Python :: 3.10
Classifier: Programming Language :: Python :: 3.11
Classifier: Programming Language :: Python :: 3.12
Classifier: Programming Language :: Python :: Implementation :: CPython
Requires-Dist: attrs >=23.1.0
Requires-Dist: crowsetta >=5.1.0
Requires-Dist: dask[dataframe] >=2.10.1
Requires-Dist: h5netcdf >= 1.3.0
Requires-Dist: librosa >= 0.10.2.post1
Requires-Dist: matplotlib >=3.7.1
Requires-Dist: numpy >=1.24.0
Requires-Dist: pandas >= 1.4.0
Requires-Dist: pooch >= 1.8.1
Requires-Dist: scipy >=1.9.0
Requires-Dist: SoundFile >=0.12.1
Requires-Dist: xarray >= 2023.11.0
Requires-Dist: twine >=3.7.1 ; extra == "dev"
Requires-Dist: black >=21.12b0 ; extra == "dev"
Requires-Dist: ipython >=8.0.0 ; extra == "dev"
Requires-Dist: nox >= 2022.1.7 ; extra == "dev"
Requires-Dist: vocalpy[doc, test] ; extra == "dev"
Requires-Dist: hdbscan>=0.8.40 ; extra == "doc"
Requires-Dist: ipython != 8.7.0 ; extra == "doc"
Requires-Dist: jupyterlab >=3.0.3 ; extra == "doc"
Requires-Dist: jupytext >=1.13.8 ; extra == "doc"
Requires-Dist: myst-nb >=0.15.0 ; extra == "doc"
Requires-Dist: numpydoc >=1.6.0 ; extra == "doc"
Requires-Dist: scikit-learn>=1.5.2 ; extra == "doc"
Requires-Dist: seaborn >=0.13.2 ; extra == "doc"
Requires-Dist: Sphinx >=3.4.3 ; extra == "doc"
Requires-Dist: sphinx-autobuild >= 2021.3.14 ; extra == "doc"
Requires-Dist: sphinx-book-theme >=0.3.2 ; extra == "doc"
Requires-Dist: sphinx-copybutton >=0.4.0 ; extra == "doc"
Requires-Dist: sphinx-design >=0.2.0 ; extra == "doc"
Requires-Dist: sphinxext-opengraph  >=0.5.1 ; extra == "doc"
Requires-Dist: sphinx-tabs >= 3.3.1 ; extra == "doc"
Requires-Dist: umap-learn>=0.5.7 ; extra == "doc"
Requires-Dist: pytest >=6.2.5 ; extra == "test"
Requires-Dist: pytest-cov >=2.11.1 ; extra == "test"
Requires-Dist: pytest-xdist >=3.2.0 ; extra == "test"
Project-URL: Docs, https://biosound.readthedocs.io
Project-URL: Home, https://github.com/biosound-org/biosound
Provides-Extra: dev
Provides-Extra: doc
Provides-Extra: test
